rpckit/__init__.py
rpckit/auth.py
rpckit/codec.py
rpckit/constants.py
rpckit/decorators.py
rpckit/exceptions.py
rpckit/function.py
rpckit/rpc.py
rpckit/transport.py
tests/__init__.py
tests/test_decorator.py
tests/test_decorator_sync.py
tests/test_rpc.py
tests/test_rpc_sync.py
cadmean_rpckit-0.2.dist-info/LICENSE
cadmean_rpckit-0.2.dist-info/METADATA
cadmean_rpckit-0.2.dist-info/WHEEL
cadmean_rpckit-0.2.dist-info/top_level.txt
cadmean_rpckit-0.2.dist-info/RECORD
