Metadata-Version: 2.1
Name: cadmean-rpckit
Version: 0.2
Summary: A cadRPC client library for Python
Home-page: https://github.com/cadmean-ru/pythonRPCKit
Author: Aleksei Kritskov
Author-email: krickov.aleksey@cadmean.ru
License: UNKNOWN
Platform: UNKNOWN
Classifier: Programming Language :: Python :: 3
Classifier: License :: OSI Approved :: MIT License
Classifier: Operating System :: OS Independent
Requires-Python: >=3.5
